LICENSE.txt
MANIFEST.in
README
README.rst
setup.cfg
setup.py
doc/Makefile
doc/examples/geo_hrit.py
doc/examples/polar_aapp1b.py
doc/examples/polar_segments.py
doc/source/conf.py
doc/source/image.rst
doc/source/index.rst
doc/source/input.rst
doc/source/install.rst
doc/source/pp.rst
doc/source/quickstart.rst
doc/source/saturn.rst
etc/DREOS-Aqua.cfg.template
etc/DREOS-Terra.cfg.template
etc/EARSMetop-A.cfg.template
etc/EARSMetop-B.cfg.template
etc/EARSNOAA-19.cfg.template
etc/EARSSuomi-NPPs.cfg.template
etc/Electro-L_N1.cfg.template
etc/FY-3A.cfg.template
etc/FY-3B.cfg.template
etc/GDSMetop-B.cfg.template
etc/GOES-13.cfg.template
etc/GOES-15.cfg.template
etc/Himawari-6.cfg.template
etc/Himawari-7.cfg.template
etc/Himawari-8.cfg.template
etc/Meteosat-10.cfg.template
etc/Meteosat-11.cfg.template
etc/Meteosat-7.cfg.template
etc/Meteosat-9.cfg.template
etc/Metop-B.cfg.template
etc/NOAA-15.cfg.template
etc/NOAA-18.cfg.template
etc/NOAA-19.cfg.template
etc/Suomi-NPP.cfg.template
etc/TerraSAR-X.cfg.template
etc/areas.def.template
etc/eps_avhrrl1b_6.5.xml
etc/geo_image.cfg
etc/hsaf10.cfg.template
etc/metop.ASCAT.cfg.template
etc/mpop.cfg.template
etc/ninjotiff_products.cfg
etc/ninjotiff_products.cfg.template
etc/noaa11.cfg.template
etc/noaa12.cfg.template
etc/noaa18-gac.cfg.template
etc/noaa18-lac.cfg.template
etc/odyssey.cfg.template
etc/s2a.cfg.template
etc/sentinel1a.cfg.template
etc/sentinel1b.cfg.template
mpop/__init__.py
mpop/channel.py
mpop/compositer.py
mpop/plugin_base.py
mpop/projector.py
mpop/scene.py
mpop/tools.py
mpop/utils.py
mpop/version.py
mpop.egg-info/PKG-INFO
mpop.egg-info/SOURCES.txt
mpop.egg-info/dependency_links.txt
mpop.egg-info/not-zip-safe
mpop.egg-info/requires.txt
mpop.egg-info/top_level.txt
mpop/imageo/HRWimage.py
mpop/imageo/TRTimage.py
mpop/imageo/__init__.py
mpop/imageo/geo_image.py
mpop/imageo/image.py
mpop/imageo/image_processing.py
mpop/imageo/palettes.py
mpop/imageo/formats/__init__.py
mpop/imageo/formats/ninjotiff.py
mpop/imageo/formats/tifffile.py
mpop/imageo/formats/writer_options.py
mpop/instruments/__init__.py
mpop/instruments/modis.py
mpop/instruments/s2_composites.py
mpop/instruments/sarx.py
